rtdl_revisiting_models.py
rtdl_revisiting_models-0.0.2.dist-info/LICENSE
rtdl_revisiting_models-0.0.2.dist-info/WHEEL
rtdl_revisiting_models-0.0.2.dist-info/METADATA
rtdl_revisiting_models-0.0.2.dist-info/RECORD
